pyfujitsugeneral/__init__.py
pyfujitsugeneral/client.py
pyfujitsugeneral/const.py
pyfujitsugeneral/exceptions.py
pyfujitsugeneral/splitAC.py
pyfujitsugeneral/utils.py
pyfujitsugeneral-2.0.33.dist-info/LICENSE
pyfujitsugeneral-2.0.33.dist-info/METADATA
pyfujitsugeneral-2.0.33.dist-info/WHEEL
pyfujitsugeneral-2.0.33.dist-info/top_level.txt
pyfujitsugeneral-2.0.33.dist-info/RECORD
