Metadata-Version: 2.1
Name: pyfujitsugeneral
Version: 2.0.33
Summary: Python Library for interacting with Fujitsu General split air conditioners API
Author-email: "Fabio Mauro, Mehdi Modarressi" <bigmoby.pymeianlike@gmail.com>
License: MIT License
Project-URL: Homepage, https://github.com/bigmoby/pyfujitsugeneral
Project-URL: Source Code, https://github.com/bigmoby/pyfujitsugeneral
Project-URL: Bug Reports, https://github.com/bigmoby/pyfujitsugeneral/issues
Keywords: Fujitsu General air conditioners
Platform: any
Classifier: Development Status :: 5 - Production/Stable
Classifier: Intended Audience :: Developers
Classifier: License :: OSI Approved :: MIT License
Classifier: Operating System :: OS Independent
Classifier: Programming Language :: Python :: 3.11
Classifier: Topic :: Software Development :: Libraries
Requires-Python: >=3.11.0
License-File: LICENSE
Requires-Dist: requests
Requires-Dist: certifi
Requires-Dist: chardet
Requires-Dist: idna
Requires-Dist: urllib3
Requires-Dist: numpy
